NanoImagingPack/DeviceControll.py
NanoImagingPack/FileUtils.py
NanoImagingPack/PhotonCalibrationExample.py
NanoImagingPack/TestDampEdge.py
NanoImagingPack/TestPSFSim.py
NanoImagingPack/__init__.py
NanoImagingPack/alignment.py
NanoImagingPack/config.py
NanoImagingPack/coordinates.py
NanoImagingPack/fitting.py
NanoImagingPack/functions.py
NanoImagingPack/image.py
NanoImagingPack/mask.py
NanoImagingPack/microscopy.py
NanoImagingPack/nditerator.py
NanoImagingPack/noise.py
NanoImagingPack/separables.py
NanoImagingPack/simPSF.py
NanoImagingPack/simulations.py
NanoImagingPack/test.py
NanoImagingPack/transformations.py
NanoImagingPack/util.py
NanoImagingPack/view.py
NanoImagingPack/view5d.py
NanoImagingPack/view5d_pyjnius.py
NanoImagingPack/EXTERNAL/Gohlke_czi_reader.py
NanoImagingPack/EXTERNAL/Gohlke_helper_fcts.py
NanoImagingPack/EXTERNAL/__init__.py
NanoImagingPack/EXTERNAL/contrib.py
NanoImagingPack/examples/Example_AbberatedPSF.py
NanoImagingPack/examples/Example_SeparableConvolution.py
NanoImagingPack/examples/Example_SimpleBeamPropagation.py
NanoImagingPack/examples/Example_spatiallyVaryingConvolution.py
NanoImagingPack/examples/Exampmle_ManualRegistration.py
NanoImagingPack/examples/ISM_Simulation_simple.py
NanoImagingPack/resources/MITO_SIM.tif
NanoImagingPack/resources/View5D_.jar
NanoImagingPack/resources/__init__.py
NanoImagingPack/resources/erika.tif
NanoImagingPack/resources/house.tif
NanoImagingPack/resources/lena.tif
NanoImagingPack/resources/obj3d.tif
NanoImagingPack/resources/orka.tif
NanoImagingPack/resources/psf3d.tif
NanoImagingPack/resources/resolution_512.tif
NanoImagingPack/resources/resolution_512old.tif
NanoImagingPack/resources/resolution_fine.tif
NanoImagingPack/sim/Make_SIM_OTF.py
NanoImagingPack/sim/REP_FILE.py
NanoImagingPack/sim/__init__.py
NanoImagingPack/sim/create_grating.py
NanoImagingPack/sim/find_grating.py
NanoImagingPack/sim/peak_finder.py
NanoImagingPack/sim/reconstruction.py
NanoImagingPack/sim/system.py
NanoImagingPack-2.1.4.dist-info/METADATA
NanoImagingPack-2.1.4.dist-info/WHEEL
NanoImagingPack-2.1.4.dist-info/top_level.txt
NanoImagingPack-2.1.4.dist-info/RECORD
