Metadata-Version: 2.1
Name: NanoImagingPack
Version: 2.1.4
Summary: An image processing package meant for use in the optics and microscopy community
Author: Christian Karras, Rainer Heintzmann
Author-email: christian-karras@gmx.de, heintzmann@gmail.com
Classifier: Programming Language :: Python :: 3
Classifier: License :: OSI Approved :: GNU General Public License (GPL)
Classifier: Operating System :: OS Independent
Requires-Dist: numpy >=1.16
Requires-Dist: scipy
Requires-Dist: tifffile
Requires-Dist: imageio
Requires-Dist: matplotlib
Requires-Dist: ruamel.yaml
Requires-Dist: tkinterdnd2
Requires-Dist: clize
Provides-Extra: napari
Requires-Dist: napari ; extra == 'napari'
